littlelee_text_writer/__init__.py
littlelee_text_writer/server.py
littlelee_text_writer-0.1.0.dist-info/METADATA
littlelee_text_writer-0.1.0.dist-info/WHEEL
littlelee_text_writer-0.1.0.dist-info/entry_points.txt
littlelee_text_writer-0.1.0.dist-info/RECORD
