Metadata-Version: 2.4
Name: littlelee-text-writer
Version: 0.1.0
Summary: Add your description here
Author-email: littlelee2022' <eun0lee@gmail.com>
Requires-Python: >=3.12
Requires-Dist: build>=1.3.0
Requires-Dist: mcp[cli]>=1.24.0
Requires-Dist: twine>=6.2.0
